[
  { "name": "Ali Shaaban", "team": "Inspire", "isGK": false, "imageUrl": null },
  { "name": "Mahmoud Hamed", "team": "Inspire", "isGK": false, "imageUrl": null },
  { "name": "Ali Ahmed", "team": "Inspire", "isGK": false, "imageUrl": null },
  { "name": "Mohamed Ayman", "team": "Inspire", "isGK": false, "imageUrl": null },
  { "name": "Helal", "team": "Inspire", "isGK": false, "imageUrl": null },
  { "name": "Omar Kassas", "team": "Inspire", "isGK": false, "imageUrl": null },
  { "name": "Omar Gomaa", "team": "Inspire", "isGK": false, "imageUrl": null },
  { "name": "Omar Shabana", "team": "Inspire", "isGK": false, "imageUrl": null },
  { "name": "Khaled Hussien", "team": "Inspire", "isGK": false, "imageUrl": null },
  { "name": "Adam Wahbie", "team": "Inspire", "isGK": false, "imageUrl": null }
]
